deform/TODO
deform/__init__.py
deform/compat.py
deform/decorator.py
deform/exception.py
deform/field.py
deform/form.py
deform/i18n.py
deform/interfaces.py
deform/renderer.py
deform/schema.py
deform/template.py
deform/utils.py
deform/widget.py
deform/locale/deform.pot
deform/locale/cs/LC_MESSAGES/deform.mo
deform/locale/cs/LC_MESSAGES/deform.po
deform/locale/da/LC_MESSAGES/deform.mo
deform/locale/da/LC_MESSAGES/deform.po
deform/locale/de/LC_MESSAGES/deform.mo
deform/locale/de/LC_MESSAGES/deform.po
deform/locale/el/LC_MESSAGES/deform.mo
deform/locale/el/LC_MESSAGES/deform.po
deform/locale/es/LC_MESSAGES/deform.mo
deform/locale/es/LC_MESSAGES/deform.po
deform/locale/fi/LC_MESSAGES/deform.mo
deform/locale/fi/LC_MESSAGES/deform.po
deform/locale/fr/LC_MESSAGES/deform.mo
deform/locale/fr/LC_MESSAGES/deform.po
deform/locale/it/LC_MESSAGES/deform.mo
deform/locale/it/LC_MESSAGES/deform.po
deform/locale/ja/LC_MESSAGES/deform.mo
deform/locale/ja/LC_MESSAGES/deform.po
deform/locale/nl/LC_MESSAGES/deform.mo
deform/locale/nl/LC_MESSAGES/deform.po
deform/locale/pl/LC_MESSAGES/deform.mo
deform/locale/pl/LC_MESSAGES/deform.po
deform/locale/pt/LC_MESSAGES/deform.mo
deform/locale/pt/LC_MESSAGES/deform.po
deform/locale/pt_BR/LC_MESSAGES/deform.mo
deform/locale/pt_BR/LC_MESSAGES/deform.po
deform/locale/ru/LC_MESSAGES/deform.mo
deform/locale/ru/LC_MESSAGES/deform.po
deform/locale/sv/LC_MESSAGES/deform.mo
deform/locale/sv/LC_MESSAGES/deform.po
deform/locale/sw_KE/LC_MESSAGES/deform.mo
deform/locale/sw_KE/LC_MESSAGES/deform.po
deform/locale/zh/LC_MESSAGES/deform.mo
deform/locale/zh/LC_MESSAGES/deform.po
deform/locale/zh_CN/LC_MESSAGES/deform.mo
deform/locale/zh_CN/LC_MESSAGES/deform.po
deform/locale/zh_Hans/LC_MESSAGES/deform.mo
deform/locale/zh_Hans/LC_MESSAGES/deform.po
deform/locale/zh_Hant/LC_MESSAGES/deform.mo
deform/locale/zh_Hant/LC_MESSAGES/deform.po
deform/static/css/bootstrap.min.css
deform/static/css/form.css
deform/static/css/pickadate-classic.date.min.css
deform-2.0.15.dist-info/LICENSE.txt
deform-2.0.15.dist-info/METADATA
deform-2.0.15.dist-info/WHEEL
deform-2.0.15.dist-info/top_level.txt
deform-2.0.15.dist-info/RECORD
