Metadata-Version: 2.1
Name: deform
Version: 2.0.15
Summary: Form library with advanced features like nested forms
Home-page: https://docs.pylonsproject.org/projects/deform/en/latest/
Author: Chris McDonough, Agendaless Consulting
Author-email: pylons-discuss@googlegroups.com
Maintainer: Steve Piercy
Maintainer-email: web@stevepiercy.com
License: BSD-derived
Project-URL: Documentation, https://docs.pylonsproject.org/projects/deform/en/2.0-branch/
Project-URL: Changelog, https://docs.pylonsproject.org/projects/deform/en/2.0-branch/changes.html
Project-URL: Issue Tracker, https://github.com/Pylons/deform/issues
Keywords: web forms form generation schema validation pyramid
Platform: UNKNOWN
Classifier: Intended Audience :: Developers
Classifier: License :: Repoze Public License
Classifier: Programming Language :: Python
Classifier: Programming Language :: Python :: 2.7
Classifier: Programming Language :: Python :: 3
Classifier: Programming Language :: Python :: 3.5
Classifier: Programming Language :: Python :: 3.6
Classifier: Programming Language :: Python :: 3.7
Classifier: Programming Language :: Python :: 3.8
Classifier: Programming Language :: Python :: 3.9
Classifier: Programming Language :: Python :: Implementation :: CPython
Classifier: Programming Language :: Python :: Implementation :: PyPy
Provides-Extra: testing
Provides-Extra: dev
Provides-Extra: functional
Provides-Extra: lint
Provides-Extra: docs
